fbleau-0.3.2.dist-info/METADATA
fbleau-0.3.2.dist-info/WHEEL
fbleau.cpython-37m-x86_64-linux-gnu.so
fbleau-0.3.2.dist-info/RECORD
