Metadata-Version: 2.1
Name: fbleau
Version: 0.3.2
Summary: A tool for measuring black-box security via Machine Learning
Author: Giovanni Cherubin <g.chers@gmail.com>
Author-Email: Giovanni Cherubin <g.chers@gmail.com>
License: MIT
